[{"query": "multi task learning with attention", "docno": "4150", "label": 5}, {"query": "multi task learning with attention", "docno": "4148", "label": 5}, {"query": "multi task learning with attention", "docno": "15068", "label": 5}, {"query": "multi task learning with attention", "docno": "9563", "label": 5}, {"query": "multi task learning with attention", "docno": "6822", "label": 2}, {"query": "multi task learning with attention", "docno": "9804", "label": 1}, {"query": "multi task learning with attention", "docno": "6588", "label": 2}, {"query": "multi task learning with attention", "docno": "14713", "label": 3}, {"query": "multi task learning with attention", "docno": "5027", "label": 3}, {"query": "multi task learning with attention", "docno": "1536", "label": 1}, {"query": "multi task learning with attention", "docno": "7813", "label": 1}, {"query": "multi task learning with attention", "docno": "10112", "label": 1}, {"query": "multi task learning with attention", "docno": "11219", "label": 1}, {"query": "multi task learning with attention", "docno": "2688", "label": 1}, {"query": "multi task learning with attention", "docno": "5333", "label": 4}, {"query": "multi task learning with attention", "docno": "5787", "label": 1}, {"query": "multi task learning with attention", "docno": "1439", "label": 3}, {"query": "multi task learning with attention", "docno": "3339", "label": 2}, {"query": "multi task learning with attention", "docno": "4391", "label": 2}, {"query": "multi task learning with attention", "docno": "9439", "label": 2}, {"query": "multi task learning with attention", "docno": "4109", "label": 2}, {"query": "multi task learning with attention", "docno": "13756", "label": 1}, {"query": "multi task learning with attention", "docno": "11539", "label": 3}, {"query": "multi task learning with attention", "docno": "12565", "label": 5}, {"query": "multi task learning with attention", "docno": "1856", "label": 2}, {"query": "multi task learning with attention", "docno": "9319", "label": 2}, {"query": "multi task learning with attention", "docno": "14027", "label": 3}, {"query": "multi task learning with attention", "docno": "2064", "label": 2}, {"query": "multi task learning with attention", "docno": "5520", "label": 2}, {"query": "multi task learning with attention", "docno": "3409", "label": 4}, {"query": "multi task learning with attention", "docno": "10714", "label": 2}, {"query": "multi task learning with attention", "docno": "1763", "label": 2}, {"query": "multi task learning with attention", "docno": "1160", "label": 3}, {"query": "multi task learning with attention", "docno": "11212", "label": 4}, {"query": "multi task learning with attention", "docno": "5887", "label": 2}, {"query": "multi task learning with attention", "docno": "14447", "label": 2}, {"query": "multi task learning with attention", "docno": "5095", "label": 1}, {"query": "multi task learning with attention", "docno": "11975", "label": 1}, {"query": "multi task learning with attention", "docno": "1848", "label": 2}, {"query": "multi task learning with attention", "docno": "2241", "label": 3}, {"query": "multi task learning with attention", "docno": "13714", "label": 3}, {"query": "multi task learning with attention", "docno": "7767", "label": 3}, {"query": "multi task learning with attention", "docno": "13254", "label": 2}, {"query": "multi task learning with attention", "docno": "9416", "label": 3}, {"query": "multi task learning with attention", "docno": "13573", "label": 2}, {"query": "multi task learning with attention", "docno": "5721", "label": 2}, {"query": "multi task learning with attention", "docno": "4094", "label": 2}, {"query": "multi task learning with attention", "docno": "3307", "label": 2}, {"query": "multi task learning with attention", "docno": "12472", "label": 3}, {"query": "multi task learning with attention", "docno": "3566", "label": 1}]